dbpackagesqtx/__init__.py
dbpackagesqtx-1.0.dist-info/METADATA
dbpackagesqtx-1.0.dist-info/WHEEL
dbpackagesqtx-1.0.dist-info/top_level.txt
dbpackagesqtx-1.0.dist-info/RECORD
