Metadata-Version: 2.1
Name: dbpackagesqtx
Version: 1.0
Summary: database connection strings
Home-page: http://github.com/storborg/funniest
Author: Flying Circus
Author-email: flyingcircus@example.com
License: MIT
Platform: UNKNOWN
Requires-Dist: phoenixdb
